blueprints_pb2.py
blueprints_pb2_grpc.py
client_wrapper.py
common_types_pb2.py
common_types_pb2_grpc.py
crmsfa_pb2.py
crmsfa_pb2_grpc.py
dataset_utils.py
forms_pb2.py
forms_pb2_grpc.py
hello_pb2.py
hello_pb2_grpc.py
helloworld_pb2.py
helloworld_pb2_grpc.py
io_utils.py
json_utils.py
mess_pb2.py
mess_pb2_grpc.py
metainfo_pb2.py
metainfo_pb2_grpc.py
nlpserv_pb2.py
nlpserv_pb2_grpc.py
options_pb2.py
options_pb2_grpc.py
protobuf_utils.py
resources_pb2.py
resources_pb2_grpc.py
services_common_pb2.py
services_common_pb2_grpc.py
simple_pb2.py
simple_pb2_grpc.py
users_pb2.py
users_pb2_grpc.py
users_types_pb2.py
users_types_pb2_grpc.py
values_pb2.py
values_pb2_grpc.py
actions/procs/__init__.py
actions/procs/actions.py
actions/procs/concert_actions.py
actions/procs/myactions.py
actions/procs/restaurant_form.py
augmentor/__init__.py
augmentor/add_fun.py
augmentor/ag_bar.py
augmentor/chart_fun.py
augmentor/cli.py
augmentor/context.py
augmentor/corpus_fun.py
augmentor/corpus_tool.py
augmentor/display_fun.py
augmentor/entity_fun.py
augmentor/maps_fun.py
augmentor/odoo_fun.py
augmentor/parse_fun.py
augmentor/product_fun.py
augmentor/rules_fun.py
augmentor/simp_fun.py
augmentor/sl_intents_tool.py
augmentor/sl_searcher.py
augmentor/test_fun.py
augmentor/viz_fun.py
delegates/__init__.py
delegates/camera.py
delegates/check-cameras.py
delegates/geo_helper.py
delegates/helpers.py
delegates/mqtt.py
delegates/processing.py
delegates/save-captures.py
delegates/sl_altair.py
delegates/sl_charts.py
delegates/sl_dele_servs.py
delegates/sl_entities.py
delegates/sl_hello.py
delegates/sl_modules.py
delegates/sl_uber_nyc.py
delegates/sl_us.py
delegates/tests.py
delegates/validate_config.py
delegates/viewer.py
interacts/__init__.py
interacts/common.py
interacts/fn.py
interacts/json_store.py
interacts/map_store.py
interacts/nlu_parsers.py
interacts/rule_store.py
interacts/sl_corpus.py
interacts/sl_dash.py
interacts/sl_domains.py
interacts/sl_fa.py
interacts/sl_fa_006.py
interacts/sl_hi.py
sagas-0.5.0.dist-info/METADATA
sagas-0.5.0.dist-info/WHEEL
sagas-0.5.0.dist-info/entry_points.txt
sagas-0.5.0.dist-info/top_level.txt
sagas-0.5.0.dist-info/RECORD
